egui_pysync/__init__.py
egui_pysync/server.py
egui_pysync/signals.py
egui_pysync/structures.py
egui_pysync/typing.py
egui_pysync/version.py
egui_pysync-0.6.1.dist-info/METADATA
egui_pysync-0.6.1.dist-info/WHEEL
egui_pysync-0.6.1.dist-info/licenses/LICENSE
egui_pysync-0.6.1.dist-info/RECORD
