Metadata-Version: 2.4
Name: egui-pysync
Version: 0.6.1
Summary: A Python library for egui-pysync project.
Author-email: Vojtech Homola <vojhom@outlook.cz>
License: MIT License
License-File: LICENSE
Requires-Python: >=3.12
Requires-Dist: numpy
